[
    {
        "name": "Chest",
        "type": "common",
        "sprite": "/images/game/chest.png",
        "inventory": [],
        "gold": 10
    },
    {
        "name": "Mimic",
        "type": "common",
        "sprite": "/images/game/mimic.png",
        "hpMax": 20,
        "mpMax": 10,
        "strength": 2,
        "defense": 0,
        "speed": 2,
        "luck": 2,
        "xp": 5,
        "inventory": [],
        "specials": [],
        "status": {},
        "gold": 13
    },
    {
        "name": "Dungeon",
        "type": "common",
        "sprite": "/images/game/dungeon.png"
    },
    {
        "name": "Quest Board",
        "type": "common",
        "sprite": "/images/game/quest-board.png"
    },
    {
        "name": "Shop",
        "type": "common",
        "sprite": "/images/game/shop.png"
    },
    {
        "name": "Tavern",
        "type": "common",
        "sprite": "/images/game/tavern.png"
    },
    {
        "name": "Traveling Merchant",
        "type": "common",
        "sprite": "/images/game/merchant.png"
    }
]